pyMut/__init__.py
pyMut/analysis/__init__.py
pyMut/analysis/mutation_burden.py
pyMut/analysis/mutational_signature.py
pyMut/analysis/pfam_annotation.py
pyMut/analysis/smg_detection.py
pyMut/annotate/__init__.py
pyMut/annotate/actionable_mutation.py
pyMut/annotate/cosmic_cancer_annotate.py
pyMut/annotate/vep_annotate.py
pyMut/combination.py
pyMut/core.py
pyMut/data/MAF_COL_ORDER.csv
pyMut/data/__init__.py
pyMut/data/examples/COSMIC_catalogue-signatures_SBS96_v3.4/COSMIC_v3.4_SBS_GRCh37.txt
pyMut/data/examples/COSMIC_catalogue-signatures_SBS96_v3.4/COSMIC_v3.4_SBS_GRCh38.txt
pyMut/data/examples/MAF/PAAD-TP.final_analysis_set.maf.gz
pyMut/data/examples/MAF/tcga_laml.maf.gz
pyMut/data/examples/MAF/tcga_laml_VEP_annotated.maf.gz
pyMut/data/examples/MAF/tcga_laml_converted.tsv
pyMut/data/examples/MAF/tcga_laml_knownCancer_annotated.maf.gz
pyMut/data/examples/VCF/subset_1k_variants_ALL.chr10.shapeit2_integrated_snvindels_v2a_27022019.GRCh38.phased.vcf
pyMut/data/examples/VCF/subset_1k_variants_ALL.chr10.shapeit2_integrated_snvindels_v2a_27022019.GRCh38.phased_vep_protein_gene_variant_class.vcf
pyMut/data/examples/VCF/subset_50k_variants_vep_protein_gene_variant_class.vcf.gz
pyMut/data/examples/annVEP_tcga_laml/tcga_laml.maf_vep.txt
pyMut/data/examples/annVEP_tcga_laml/tcga_laml_vep.txt
pyMut/data/examples/annVEP_tcga_laml/tcga_laml_vep.txt_warnings.txt
pyMut/data/examples/output_oncokb_example.json
pyMut/data/rna_cancer_consensus.json
pyMut/filters/__init__.py
pyMut/filters/chrom_sample_filter.py
pyMut/filters/genomic_range.py
pyMut/filters/pass_filter.py
pyMut/filters/tissue_expression.py
pyMut/input.py
pyMut/output.py
pyMut/utils/__init__.py
pyMut/utils/constants.py
pyMut/utils/create_subset.py
pyMut/utils/data_processing.py
pyMut/utils/database.py
pyMut/utils/fields.py
pyMut/utils/format.py
pyMut/utils/merge_vep_annotation.py
pyMut/version.py
pyMut/visualizations/__init__.py
pyMut/visualizations/oncoplot.py
pyMut/visualizations/summary.py
pymut_bio-0.1.4.dist-info/LICENSE
pymut_bio-0.1.4.dist-info/METADATA
pymut_bio-0.1.4.dist-info/WHEEL
pymut_bio-0.1.4.dist-info/RECORD
