Metadata-Version: 2.3
Name: pymut-bio
Version: 0.1.4
Summary: A Python library for genetic mutations
License: MIT License
Author: Luis Ruiz Moreno
Author-email: lruizm4@alumnos.nebrija.es
Requires-Python: >=3.10,<3.13
Classifier: Development Status :: 4 - Beta
Classifier: Programming Language :: Python :: 3
Classifier: Programming Language :: Python :: 3 :: Only
Classifier: Operating System :: OS Independent
Classifier: Topic :: Scientific/Engineering :: Bio-Informatics
Classifier: License :: OSI Approved :: BSD License
Provides-Extra: docs
Provides-Extra: viz
Requires-Dist: duckdb (>=1.3.2,<2.0.0)
Requires-Dist: fastparquet (>=2024.11.0,<2025.0.0)
Requires-Dist: matplotlib (>=3.10,<4) ; extra == "viz"
Requires-Dist: matplotlib (>=3.10.3,<4.0.0)
Requires-Dist: mkdocs (>=1.6,<2) ; extra == "docs"
Requires-Dist: mkdocs (>=1.6.1,<2.0.0)
Requires-Dist: numpy (==1.26.*)
Requires-Dist: pandas (>=2.3.1,<3.0.0)
Requires-Dist: pyarrow (>=14.0.2,<15.0.0)
Requires-Dist: pyensembl (>=2.3.13,<3.0.0)
Requires-Dist: pyfaidx (>=0.8.1.4,<0.9.0.0)
Requires-Dist: requests (>=2.32.4,<3.0.0)
Requires-Dist: scikit-learn (>=1.7.1,<2.0.0)
Requires-Dist: scipy (==1.11.*)
Requires-Dist: seaborn (>=0.13,<0.14) ; extra == "viz"
Requires-Dist: seaborn (>=0.13.2,<0.14.0)
Requires-Dist: urllib3 (>=2.5.0,<3.0.0)
Project-URL: Documentation, https://luisruimor.github.io/pyMut/
Project-URL: Homepage, https://luisruimor.github.io/pyMut/
Project-URL: Issues, https://github.com/Luisruimor/pyMut/issues
Project-URL: Repository, https://github.com/Luisruimor/pyMut
